AUTHORS
CONTRIBUTING.md
LICENSE
MANIFEST.in
README.md
setup.cfg
setup.py
bpptkg_meteo.egg-info/PKG-INFO
bpptkg_meteo.egg-info/SOURCES.txt
bpptkg_meteo.egg-info/dependency_links.txt
bpptkg_meteo.egg-info/not-zip-safe
bpptkg_meteo.egg-info/requires.txt
bpptkg_meteo.egg-info/top_level.txt
meteo/__init__.py
meteo/singleton.py
meteo/db/__init__.py
meteo/db/engine.py
meteo/db/ops.py
meteo/db/sessions.py
meteo/models/__init__.py
meteo/models/base.py
meteo/models/bbd.py
meteo/models/cr6.py
meteo/models/jra.py
meteo/models/jro.py
meteo/models/kal.py
meteo/models/kla.py
meteo/models/lbh.py
meteo/models/ngep.py
meteo/models/psbb.py
meteo/models/sel.py
meteo/parser/__init__.py
meteo/parser/fields.py
meteo/parser/vaisala.py
meteo/utils/__init__.py
meteo/utils/encoding.py