Metadata-Version: 2.1
Name: bpptkg-meteo
Version: 1.2.4
Summary: BPPTKG weather station data fetcher and schema tables library
Author: BPPTKG
Author-email: bpptkg@esdm.go.id
License: MIT
Classifier: Development Status :: 5 - Production/Stable
Classifier: Environment :: Console
Classifier: Operating System :: POSIX :: Linux
Classifier: Intended Audience :: Science/Research
Classifier: Natural Language :: English
Classifier: Programming Language :: Python :: 3.6
Classifier: Programming Language :: Python :: 3.7
Classifier: Programming Language :: Python :: 3.8
Classifier: Programming Language :: Python :: 3.9
License-File: LICENSE
Requires-Dist: sqlalchemy
